{
  "name": "prowjobruntests_finalize",
  "description": "Finalize phase: Swap tables and rename partitions for prow_job_run_tests, prow_job_run_test_outputs, and test_analysis_by_job_by_dates",
  "steps": [
    {
      "name": "discover_releases",
      "type": "query_releases",
      "query": "SELECT DISTINCT release FROM prow_jobs ORDER BY release",
      "store_as": "releases"
    },
    {
      "name": "swap_tables",
      "type": "sql_specs",
      "spec_file": "config/specs/prowjobruntests/006_swap_partitioned_tables.json"
    },
    {
      "name": "rename_prow_job_run_tests_partitions",
      "type": "rename_partitions",
      "table": "prow_job_run_tests",
      "releases_from": "releases",
      "use_partman_format": true
    },
    {
      "name": "rename_prow_job_run_test_outputs_partitions",
      "type": "rename_partitions",
      "table": "prow_job_run_test_outputs",
      "releases_from": "releases",
      "use_partman_format": true
    },
    {
      "name": "rename_test_analysis_partitions",
      "type": "rename_partitions",
      "table": "test_analysis_by_job_by_dates",
      "releases_from": "releases",
      "use_partman_format": true
    }
  ]
}
